{
	"94002": [
		"10964",
		"6417",
		"567",
		"211",
		"131",
		"420",
		"1094",
		"2014",
		"83",
		"27"
	],
	"94005": [
		"1981",
		"1012",
		"219",
		"170",
		"78",
		"107",
		"209",
		"58",
		"128",
		"0"
	],
	"94010": [
		"17261",
		"10542",
		"404",
		"399",
		"878",
		"1571",
		"1425",
		"1999",
		"43",
		"0"
	],
	"94014": [
		"14347",
		"5272",
		"3690",
		"1013",
		"1514",
		"533",
		"700",
		"1089",
		"501",
		"35"
	],
	"94015": [
		"20876",
		"12586",
		"930",
		"408",
		"535",
		"839",
		"1156",
		"4388",
		"7",
		"27"
	],
	"94019": [
		"7254",
		"4971",
		"612",
		"371",
		"408",
		"220",
		"0",
		"229",
		"433",
		"10"
	],
	"94020": [
		"875",
		"802",
		"20",
		"11",
		"8",
		"0",
		"0",
		"0",
		"34",
		"0"
	],
	"94021": [
		"100",
		"100",
		"0",
		"0",
		"0",
		"0",
		"0",
		"0",
		"0",
		"0"
	],
	"94022": [
		"7802",
		"6369",
		"459",
		"50",
		"94",
		"136",
		"207",
		"487",
		"0",
		"0"
	],
	"94024": [
		"8156",
		"7545",
		"272",
		"58",
		"15",
		"30",
		"0",
		"229",
		"7",
		"0"
	],
	"94025": [
		"16330",
		"9937",
		"1273",
		"236",
		"1323",
		"1255",
		"790",
		"1505",
		"11",
		"0"
	],
	"94027": [
		"2538",
		"2448",
		"62",
		"0",
		"7",
		"15",
		"0",
		"6",
		"0",
		"0"
	],
	"94028": [
		"2876",
		"2485",
		"17",
		"33",
		"0",
		"58",
		"145",
		"114",
		"24",
		"0"
	],
	"94030": [
		"8325",
		"5425",
		"243",
		"268",
		"306",
		"639",
		"323",
		"1098",
		"23",
		"0"
	],
	"94037": [
		"1019",
		"972",
		"0",
		"0",
		"0",
		"0",
		"0",
		"47",
		"0",
		"0"
	],
	"94038": [
		"1199",
		"903",
		"33",
		"0",
		"0",
		"35",
		"36",
		"0",
		"192",
		"0"
	],
	"94040": [
		"14468",
		"4975",
		"1184",
		"203",
		"384",
		"676",
		"1234",
		"5647",
		"165",
		"0"
	],
	"94041": [
		"6051",
		"2113",
		"526",
		"213",
		"456",
		"407",
		"831",
		"1059",
		"446",
		"0"
	],
	"94043": [
		"12975",
		"3347",
		"2424",
		"317",
		"1072",
		"1129",
		"1459",
		"2816",
		"397",
		"14"
	],
	"94044": [
		"14548",
		"10672",
		"982",
		"195",
		"662",
		"546",
		"519",
		"874",
		"98",
		"0"
	],
	"94060": [
		"686",
		"543",
		"8",
		"18",
		"10",
		"52",
		"0",
		"10",
		"22",
		"23"
	],
	"94061": [
		"13872",
		"7499",
		"1651",
		"490",
		"601",
		"965",
		"1095",
		"1571",
		"0",
		"0"
	],
	"94062": [
		"10608",
		"8772",
		"261",
		"62",
		"123",
		"291",
		"521",
		"546",
		"32",
		"0"
	],
	"94063": [
		"9275",
		"3321",
		"866",
		"388",
		"843",
		"819",
		"623",
		"1640",
		"660",
		"115"
	],
	"94065": [
		"4929",
		"2185",
		"924",
		"27",
		"237",
		"542",
		"423",
		"547",
		"44",
		"0"
	],
	"94066": [
		"15550",
		"9015",
		"367",
		"486",
		"774",
		"1302",
		"849",
		"2749",
		"8",
		"0"
	],
	"94070": [
		"12066",
		"8377",
		"556",
		"130",
		"456",
		"766",
		"1049",
		"711",
		"21",
		"0"
	],
	"94074": [
		"94",
		"94",
		"0",
		"0",
		"0",
		"0",
		"0",
		"0",
		"0",
		"0"
	],
	"94080": [
		"21966",
		"12588",
		"2375",
		"715",
		"951",
		"1216",
		"1196",
		"2487",
		"250",
		"188"
	],
	"94085": [
		"8305",
		"2575",
		"507",
		"169",
		"535",
		"972",
		"1116",
		"2349",
		"82",
		"0"
	],
	"94086": [
		"19435",
		"5429",
		"1620",
		"340",
		"2132",
		"1883",
		"2294",
		"4969",
		"731",
		"37"
	],
	"94087": [
		"20837",
		"11602",
		"1933",
		"143",
		"1324",
		"913",
		"1453",
		"3317",
		"109",
		"43"
	],
	"94089": [
		"7779",
		"1703",
		"634",
		"54",
		"170",
		"284",
		"801",
		"1125",
		"3008",
		"0"
	],
	"94102": [
		"18713",
		"527",
		"499",
		"456",
		"709",
		"814",
		"1711",
		"13904",
		"48",
		"45"
	],
	"94103": [
		"14322",
		"364",
		"332",
		"467",
		"1669",
		"2028",
		"2038",
		"7349",
		"0",
		"75"
	],
	"94104": [
		"275",
		"0",
		"0",
		"0",
		"0",
		"0",
		"0",
		"275",
		"0",
		"0"
	],
	"94105": [
		"4651",
		"145",
		"14",
		"0",
		"14",
		"9",
		"0",
		"4444",
		"25",
		"0"
	],
	"94107": [
		"14829",
		"1317",
		"863",
		"1282",
		"1090",
		"736",
		"943",
		"8560",
		"16",
		"22"
	],
	"94108": [
		"8554",
		"55",
		"44",
		"194",
		"559",
		"851",
		"1691",
		"5128",
		"32",
		"0"
	],
	"94109": [
		"36850",
		"851",
		"433",
		"1161",
		"1867",
		"3887",
		"7565",
		"21012",
		"38",
		"36"
	],
	"94110": [
		"29276",
		"5719",
		"4049",
		"4581",
		"5439",
		"3968",
		"2308",
		"3173",
		"0",
		"39"
	],
	"94111": [
		"2643",
		"70",
		"90",
		"0",
		"0",
		"14",
		"0",
		"2469",
		"0",
		"0"
	],
	"94112": [
		"23498",
		"11515",
		"7320",
		"2101",
		"1214",
		"681",
		"331",
		"275",
		"61",
		"0"
	],
	"94114": [
		"17880",
		"3663",
		"1924",
		"3398",
		"3720",
		"2750",
		"1255",
		"1118",
		"52",
		"0"
	],
	"94115": [
		"18968",
		"1332",
		"718",
		"1333",
		"2731",
		"2987",
		"3223",
		"6644",
		"0",
		"0"
	],
	"94116": [
		"16194",
		"6607",
		"6773",
		"1183",
		"692",
		"267",
		"350",
		"285",
		"37",
		"0"
	],
	"94117": [
		"19568",
		"1501",
		"1032",
		"3114",
		"4404",
		"4348",
		"2742",
		"2412",
		"15",
		"0"
	],
	"94118": [
		"18649",
		"2491",
		"1984",
		"3718",
		"4350",
		"2581",
		"2372",
		"1144",
		"9",
		"0"
	],
	"94121": [
		"18837",
		"3710",
		"3051",
		"3318",
		"3927",
		"2557",
		"1506",
		"768",
		"0",
		"0"
	],
	"94122": [
		"23459",
		"5773",
		"6671",
		"3911",
		"2808",
		"1786",
		"1276",
		"1121",
		"19",
		"94"
	],
	"94123": [
		"15349",
		"1404",
		"787",
		"2294",
		"1979",
		"2134",
		"4726",
		"2011",
		"14",
		"0"
	],
	"94124": [
		"11096",
		"3741",
		"3249",
		"749",
		"856",
		"880",
		"481",
		"1113",
		"27",
		"0"
	],
	"94127": [
		"7659",
		"5725",
		"1377",
		"144",
		"43",
		"53",
		"201",
		"103",
		"13",
		"0"
	],
	"94128": [
		"0",
		"0",
		"0",
		"0",
		"0",
		"0",
		"0",
		"0",
		"0",
		"0"
	],
	"94129": [
		"1216",
		"85",
		"242",
		"89",
		"444",
		"193",
		"55",
		"108",
		"0",
		"0"
	],
	"94130": [
		"878",
		"15",
		"322",
		"20",
		"216",
		"288",
		"0",
		"17",
		"0",
		"0"
	],
	"94131": [
		"13787",
		"3886",
		"2518",
		"2000",
		"1545",
		"880",
		"1591",
		"1367",
		"0",
		"0"
	],
	"94132": [
		"11227",
		"3685",
		"2401",
		"296",
		"275",
		"560",
		"544",
		"3445",
		"21",
		"0"
	],
	"94133": [
		"14987",
		"405",
		"604",
		"1474",
		"2895",
		"2778",
		"1762",
		"5069",
		"0",
		"0"
	],
	"94134": [
		"12088",
		"5195",
		"4270",
		"953",
		"352",
		"526",
		"385",
		"382",
		"25",
		"0"
	],
	"94158": [
		"2705",
		"39",
		"21",
		"24",
		"23",
		"0",
		"0",
		"2598",
		"0",
		"0"
	],
	"94301": [
		"7650",
		"3945",
		"374",
		"217",
		"506",
		"775",
		"473",
		"1360",
		"0",
		"0"
	],
	"94303": [
		"14485",
		"8930",
		"880",
		"104",
		"433",
		"556",
		"905",
		"2507",
		"170",
		"0"
	],
	"94304": [
		"2099",
		"217",
		"12",
		"3",
		"71",
		"113",
		"239",
		"1444",
		"0",
		"0"
	],
	"94305": [
		"3043",
		"839",
		"230",
		"0",
		"190",
		"420",
		"95",
		"1269",
		"0",
		"0"
	],
	"94306": [
		"11315",
		"6332",
		"804",
		"106",
		"755",
		"712",
		"777",
		"1760",
		"69",
		"0"
	],
	"94401": [
		"13706",
		"4693",
		"903",
		"372",
		"917",
		"1575",
		"1113",
		"4122",
		"11",
		"0"
	],
	"94402": [
		"9770",
		"6370",
		"687",
		"319",
		"354",
		"518",
		"237",
		"1252",
		"33",
		"0"
	],
	"94403": [
		"16398",
		"8656",
		"1277",
		"355",
		"819",
		"1080",
		"877",
		"3310",
		"24",
		"0"
	],
	"94404": [
		"14406",
		"5111",
		"2883",
		"68",
		"900",
		"1130",
		"887",
		"3427",
		"0",
		"0"
	],
	"94501": [
		"26799",
		"10108",
		"1910",
		"2097",
		"2911",
		"2833",
		"1545",
		"5312",
		"21",
		"62"
	],
	"94502": [
		"5292",
		"3599",
		"1475",
		"58",
		"0",
		"0",
		"43",
		"117",
		"0",
		"0"
	],
	"94506": [
		"7567",
		"6189",
		"1184",
		"82",
		"25",
		"31",
		"31",
		"25",
		"0",
		"0"
	],
	"94507": [
		"5712",
		"5287",
		"275",
		"0",
		"5",
		"21",
		"20",
		"62",
		"42",
		"0"
	],
	"94509": [
		"23063",
		"16154",
		"1135",
		"329",
		"1283",
		"1196",
		"1265",
		"1254",
		"429",
		"18"
	],
	"94510": [
		"11463",
		"7574",
		"1014",
		"184",
		"963",
		"721",
		"316",
		"516",
		"165",
		"10"
	],
	"94512": [
		"84",
		"44",
		"0",
		"0",
		"0",
		"40",
		"0",
		"0",
		"0",
		"0"
	],
	"94513": [
		"18655",
		"16645",
		"488",
		"19",
		"274",
		"269",
		"204",
		"366",
		"385",
		"5"
	],
	"94516": [
		"69",
		"60",
		"0",
		"0",
		"0",
		"4",
		"0",
		"0",
		"4",
		"1"
	],
	"94517": [
		"4751",
		"3599",
		"619",
		"0",
		"186",
		"0",
		"14",
		"141",
		"192",
		"0"
	],
	"94518": [
		"10967",
		"6969",
		"739",
		"118",
		"586",
		"484",
		"293",
		"931",
		"832",
		"15"
	],
	"94519": [
		"7499",
		"5750",
		"400",
		"146",
		"314",
		"206",
		"78",
		"546",
		"59",
		"0"
	],
	"94520": [
		"13673",
		"5344",
		"410",
		"202",
		"883",
		"1478",
		"828",
		"3910",
		"610",
		"8"
	],
	"94521": [
		"16439",
		"10941",
		"1399",
		"174",
		"888",
		"925",
		"754",
		"1254",
		"55",
		"49"
	],
	"94523": [
		"14682",
		"8123",
		"1482",
		"286",
		"946",
		"1190",
		"418",
		"2180",
		"57",
		"0"
	],
	"94525": [
		"1582",
		"1023",
		"63",
		"260",
		"132",
		"11",
		"56",
		"37",
		"0",
		"0"
	],
	"94526": [
		"12518",
		"9601",
		"1956",
		"85",
		"220",
		"164",
		"66",
		"408",
		"18",
		"0"
	],
	"94528": [
		"382",
		"358",
		"24",
		"0",
		"0",
		"0",
		"0",
		"0",
		"0",
		"0"
	],
	"94530": [
		"10742",
		"7609",
		"484",
		"331",
		"805",
		"487",
		"259",
		"725",
		"29",
		"13"
	],
	"94531": [
		"12540",
		"11393",
		"227",
		"58",
		"78",
		"173",
		"19",
		"588",
		"4",
		"0"
	],
	"94536": [
		"25318",
		"13049",
		"3910",
		"298",
		"662",
		"896",
		"642",
		"5617",
		"244",
		"0"
	],
	"94538": [
		"21686",
		"10335",
		"2684",
		"88",
		"546",
		"593",
		"1238",
		"5904",
		"289",
		"9"
	],
	"94539": [
		"16524",
		"12930",
		"2021",
		"69",
		"299",
		"246",
		"208",
		"704",
		"47",
		"0"
	],
	"94541": [
		"21502",
		"10841",
		"2934",
		"635",
		"1277",
		"1738",
		"1247",
		"2664",
		"158",
		"8"
	],
	"94542": [
		"4606",
		"3167",
		"232",
		"39",
		"322",
		"276",
		"233",
		"316",
		"21",
		"0"
	],
	"94544": [
		"23191",
		"11303",
		"1387",
		"433",
		"1299",
		"1800",
		"1793",
		"3515",
		"1661",
		"0"
	],
	"94545": [
		"9447",
		"5993",
		"789",
		"25",
		"361",
		"472",
		"392",
		"746",
		"669",
		"0"
	],
	"94546": [
		"16980",
		"11251",
		"914",
		"283",
		"849",
		"626",
		"770",
		"1919",
		"343",
		"25"
	],
	"94547": [
		"8497",
		"5545",
		"1345",
		"65",
		"412",
		"610",
		"83",
		"394",
		"23",
		"20"
	],
	"94549": [
		"10904",
		"8724",
		"390",
		"165",
		"363",
		"203",
		"465",
		"585",
		"9",
		"0"
	],
	"94550": [
		"18100",
		"13726",
		"815",
		"210",
		"353",
		"840",
		"787",
		"1329",
		"40",
		"0"
	],
	"94551": [
		"13893",
		"9531",
		"1380",
		"291",
		"574",
		"764",
		"267",
		"620",
		"443",
		"23"
	],
	"94552": [
		"5012",
		"3936",
		"892",
		"0",
		"39",
		"25",
		"0",
		"72",
		"48",
		"0"
	],
	"94553": [
		"19378",
		"13012",
		"2355",
		"377",
		"932",
		"415",
		"573",
		"1006",
		"708",
		"0"
	],
	"94555": [
		"11505",
		"7154",
		"2675",
		"72",
		"274",
		"278",
		"164",
		"683",
		"205",
		"0"
	],
	"94556": [
		"5951",
		"4032",
		"927",
		"98",
		"246",
		"227",
		"159",
		"262",
		"0",
		"0"
	],
	"94560": [
		"13781",
		"9654",
		"1625",
		"69",
		"521",
		"548",
		"327",
		"1026",
		"11",
		"0"
	],
	"94561": [
		"11955",
		"10332",
		"303",
		"16",
		"171",
		"131",
		"104",
		"255",
		"619",
		"24"
	],
	"94563": [
		"6560",
		"6086",
		"213",
		"10",
		"19",
		"0",
		"9",
		"223",
		"0",
		"0"
	],
	"94564": [
		"7144",
		"5167",
		"540",
		"61",
		"305",
		"266",
		"327",
		"478",
		"0",
		"0"
	],
	"94565": [
		"27836",
		"18900",
		"1827",
		"528",
		"1237",
		"1295",
		"1025",
		"1646",
		"1339",
		"39"
	],
	"94566": [
		"15109",
		"10459",
		"1068",
		"212",
		"790",
		"526",
		"627",
		"1083",
		"344",
		"0"
	],
	"94568": [
		"16368",
		"8320",
		"2026",
		"153",
		"401",
		"1059",
		"795",
		"3581",
		"33",
		"0"
	],
	"94569": [
		"162",
		"100",
		"0",
		"0",
		"0",
		"38",
		"24",
		"0",
		"0",
		"0"
	],
	"94571": [
		"4281",
		"3790",
		"64",
		"17",
		"66",
		"87",
		"32",
		"33",
		"192",
		"0"
	],
	"94572": [
		"3111",
		"2460",
		"68",
		"130",
		"226",
		"44",
		"22",
		"124",
		"37",
		"0"
	],
	"94575": [
		"0",
		"0",
		"0",
		"0",
		"0",
		"0",
		"0",
		"0",
		"0",
		"0"
	],
	"94577": [
		"17438",
		"10308",
		"1442",
		"433",
		"560",
		"750",
		"713",
		"2934",
		"277",
		"21"
	],
	"94578": [
		"14507",
		"6375",
		"910",
		"862",
		"980",
		"743",
		"912",
		"3483",
		"207",
		"35"
	],
	"94579": [
		"6987",
		"5413",
		"161",
		"39",
		"27",
		"24",
		"177",
		"550",
		"568",
		"28"
	],
	"94580": [
		"8962",
		"7366",
		"624",
		"90",
		"61",
		"218",
		"99",
		"475",
		"29",
		"0"
	],
	"94582": [
		"13326",
		"8137",
		"1837",
		"70",
		"406",
		"627",
		"961",
		"1288",
		"0",
		"0"
	],
	"94583": [
		"12847",
		"8180",
		"1071",
		"77",
		"626",
		"903",
		"910",
		"1080",
		"0",
		"0"
	],
	"94585": [
		"9178",
		"7419",
		"167",
		"96",
		"419",
		"373",
		"232",
		"345",
		"127",
		"0"
	],
	"94586": [
		"400",
		"371",
		"12",
		"0",
		"0",
		"0",
		"0",
		"0",
		"17",
		"0"
	],
	"94587": [
		"21679",
		"13034",
		"3061",
		"230",
		"815",
		"485",
		"371",
		"2771",
		"883",
		"29"
	],
	"94588": [
		"11163",
		"7189",
		"1005",
		"84",
		"525",
		"460",
		"739",
		"1133",
		"23",
		"5"
	],
	"94590": [
		"16541",
		"8575",
		"657",
		"1529",
		"2021",
		"1147",
		"755",
		"1233",
		"579",
		"45"
	],
	"94591": [
		"20156",
		"15617",
		"762",
		"290",
		"875",
		"960",
		"960",
		"507",
		"161",
		"24"
	],
	"94592": [
		"257",
		"222",
		"0",
		"0",
		"35",
		"0",
		"0",
		"0",
		"0",
		"0"
	],
	"94595": [
		"10137",
		"2696",
		"1340",
		"259",
		"2114",
		"1634",
		"1086",
		"965",
		"43",
		"0"
	],
	"94596": [
		"10122",
		"3512",
		"645",
		"229",
		"352",
		"709",
		"503",
		"4172",
		"0",
		"0"
	],
	"94597": [
		"10384",
		"3812",
		"1379",
		"184",
		"779",
		"830",
		"762",
		"2609",
		"29",
		"0"
	],
	"94598": [
		"10442",
		"7081",
		"1856",
		"27",
		"469",
		"325",
		"105",
		"571",
		"8",
		"0"
	],
	"94601": [
		"16436",
		"6952",
		"783",
		"1794",
		"2761",
		"1309",
		"870",
		"1899",
		"68",
		"0"
	],
	"94602": [
		"12576",
		"7839",
		"423",
		"748",
		"1473",
		"863",
		"580",
		"638",
		"12",
		"0"
	],
	"94603": [
		"10264",
		"6630",
		"361",
		"817",
		"1096",
		"602",
		"403",
		"278",
		"72",
		"5"
	],
	"94605": [
		"17027",
		"11168",
		"1028",
		"563",
		"1543",
		"1481",
		"432",
		"809",
		"3",
		"0"
	],
	"94606": [
		"16350",
		"3449",
		"898",
		"1670",
		"2060",
		"2234",
		"2348",
		"3651",
		"36",
		"4"
	],
	"94607": [
		"12229",
		"1725",
		"822",
		"1382",
		"1238",
		"779",
		"864",
		"5346",
		"73",
		"0"
	],
	"94608": [
		"14960",
		"3667",
		"683",
		"1707",
		"1878",
		"912",
		"672",
		"5328",
		"113",
		"0"
	],
	"94609": [
		"10629",
		"3121",
		"394",
		"1569",
		"2078",
		"1243",
		"1009",
		"1215",
		"0",
		"0"
	],
	"94610": [
		"16556",
		"4640",
		"332",
		"714",
		"1563",
		"1453",
		"2372",
		"5402",
		"48",
		"32"
	],
	"94611": [
		"17593",
		"10449",
		"267",
		"487",
		"1092",
		"902",
		"907",
		"3485",
		"4",
		"0"
	],
	"94612": [
		"8633",
		"242",
		"109",
		"238",
		"268",
		"320",
		"822",
		"6587",
		"40",
		"7"
	],
	"94613": [
		"9",
		"9",
		"0",
		"0",
		"0",
		"0",
		"0",
		"0",
		"0",
		"0"
	],
	"94618": [
		"7855",
		"4749",
		"421",
		"543",
		"530",
		"181",
		"397",
		"1034",
		"0",
		"0"
	],
	"94619": [
		"9465",
		"6761",
		"321",
		"399",
		"907",
		"485",
		"267",
		"254",
		"71",
		"0"
	],
	"94621": [
		"9924",
		"5444",
		"534",
		"726",
		"1408",
		"631",
		"378",
		"737",
		"66",
		"0"
	],
	"94702": [
		"8084",
		"4199",
		"409",
		"642",
		"1113",
		"466",
		"261",
		"961",
		"0",
		"33"
	],
	"94703": [
		"9755",
		"3824",
		"485",
		"1177",
		"1589",
		"891",
		"785",
		"925",
		"79",
		"0"
	],
	"94704": [
		"8808",
		"886",
		"274",
		"328",
		"762",
		"984",
		"1380",
		"4142",
		"52",
		"0"
	],
	"94705": [
		"6259",
		"3232",
		"205",
		"712",
		"794",
		"436",
		"496",
		"338",
		"46",
		"0"
	],
	"94706": [
		"8327",
		"4277",
		"293",
		"418",
		"548",
		"600",
		"713",
		"1454",
		"24",
		"0"
	],
	"94707": [
		"5315",
		"4794",
		"91",
		"168",
		"49",
		"29",
		"92",
		"73",
		"19",
		"0"
	],
	"94708": [
		"4998",
		"4498",
		"128",
		"245",
		"56",
		"71",
		"0",
		"0",
		"0",
		"0"
	],
	"94709": [
		"5689",
		"1089",
		"169",
		"602",
		"696",
		"1049",
		"971",
		"1113",
		"0",
		"0"
	],
	"94710": [
		"3060",
		"1332",
		"113",
		"445",
		"492",
		"146",
		"210",
		"313",
		"9",
		"0"
	],
	"94720": [
		"89",
		"11",
		"0",
		"0",
		"14",
		"0",
		"23",
		"41",
		"0",
		"0"
	],
	"94801": [
		"10598",
		"5100",
		"778",
		"1186",
		"1243",
		"760",
		"537",
		"987",
		"7",
		"0"
	],
	"94803": [
		"9914",
		"7345",
		"623",
		"162",
		"227",
		"449",
		"306",
		"681",
		"99",
		"22"
	],
	"94804": [
		"15833",
		"8913",
		"1061",
		"1311",
		"1969",
		"1235",
		"652",
		"621",
		"41",
		"30"
	],
	"94805": [
		"5528",
		"4444",
		"100",
		"296",
		"422",
		"100",
		"106",
		"60",
		"0",
		"0"
	],
	"94806": [
		"20600",
		"11357",
		"1293",
		"417",
		"1147",
		"1219",
		"1720",
		"2860",
		"564",
		"23"
	],
	"94850": [
		"0",
		"0",
		"0",
		"0",
		"0",
		"0",
		"0",
		"0",
		"0",
		"0"
	],
	"94901": [
		"16347",
		"8160",
		"1422",
		"839",
		"978",
		"1253",
		"1561",
		"2062",
		"27",
		"45"
	],
	"94903": [
		"12760",
		"7098",
		"1399",
		"41",
		"360",
		"557",
		"746",
		"2196",
		"363",
		"0"
	],
	"94904": [
		"5580",
		"3144",
		"325",
		"74",
		"226",
		"535",
		"654",
		"437",
		"139",
		"46"
	],
	"94920": [
		"6110",
		"3846",
		"505",
		"177",
		"537",
		"650",
		"266",
		"129",
		"0",
		"0"
	],
	"94924": [
		"818",
		"712",
		"5",
		"57",
		"13",
		"6",
		"0",
		"0",
		"25",
		"0"
	],
	"94925": [
		"4303",
		"2720",
		"508",
		"111",
		"167",
		"218",
		"185",
		"394",
		"0",
		"0"
	],
	"94930": [
		"4055",
		"2575",
		"450",
		"259",
		"94",
		"137",
		"168",
		"263",
		"109",
		"0"
	],
	"94933": [
		"394",
		"340",
		"0",
		"0",
		"31",
		"0",
		"0",
		"0",
		"23",
		"0"
	],
	"94937": [
		"811",
		"752",
		"27",
		"26",
		"0",
		"0",
		"0",
		"0",
		"6",
		"0"
	],
	"94938": [
		"385",
		"271",
		"42",
		"65",
		"0",
		"0",
		"0",
		"0",
		"7",
		"0"
	],
	"94939": [
		"3302",
		"1851",
		"160",
		"68",
		"147",
		"223",
		"339",
		"514",
		"0",
		"0"
	],
	"94941": [
		"14024",
		"9746",
		"1008",
		"454",
		"383",
		"739",
		"641",
		"1039",
		"14",
		"0"
	],
	"94945": [
		"7129",
		"5032",
		"614",
		"219",
		"246",
		"179",
		"322",
		"312",
		"193",
		"12"
	],
	"94946": [
		"367",
		"348",
		"3",
		"16",
		"0",
		"0",
		"0",
		"0",
		"0",
		"0"
	],
	"94947": [
		"10044",
		"6947",
		"1299",
		"0",
		"390",
		"470",
		"140",
		"781",
		"17",
		"0"
	],
	"94949": [
		"7311",
		"3532",
		"1362",
		"132",
		"463",
		"562",
		"228",
		"488",
		"544",
		"0"
	],
	"94950": [
		"23",
		"23",
		"0",
		"0",
		"0",
		"0",
		"0",
		"0",
		"0",
		"0"
	],
	"94956": [
		"1062",
		"869",
		"69",
		"44",
		"56",
		"0",
		"0",
		"24",
		"0",
		"0"
	],
	"94957": [
		"399",
		"389",
		"5",
		"0",
		"5",
		"0",
		"0",
		"0",
		"0",
		"0"
	],
	"94960": [
		"6760",
		"5543",
		"273",
		"129",
		"139",
		"224",
		"329",
		"123",
		"0",
		"0"
	],
	"94963": [
		"205",
		"171",
		"16",
		"18",
		"0",
		"0",
		"0",
		"0",
		"0",
		"0"
	],
	"94964": [
		"100",
		"100",
		"0",
		"0",
		"0",
		"0",
		"0",
		"0",
		"0",
		"0"
	],
	"94965": [
		"6386",
		"2462",
		"854",
		"717",
		"497",
		"660",
		"385",
		"519",
		"11",
		"281"
	],
	"94970": [
		"923",
		"893",
		"15",
		"15",
		"0",
		"0",
		"0",
		"0",
		"0",
		"0"
	],
	"94973": [
		"735",
		"649",
		"50",
		"17",
		"19",
		"0",
		"0",
		"0",
		"0",
		"0"
	],
	"95002": [
		"559",
		"316",
		"71",
		"34",
		"46",
		"14",
		"0",
		"0",
		"78",
		"0"
	],
	"95006": [
		"4808",
		"4273",
		"309",
		"56",
		"60",
		"16",
		"0",
		"7",
		"87",
		"0"
	],
	"95008": [
		"19131",
		"8562",
		"2327",
		"372",
		"1893",
		"978",
		"1301",
		"3303",
		"357",
		"38"
	],
	"95014": [
		"22480",
		"12234",
		"2925",
		"353",
		"1452",
		"1193",
		"1259",
		"3035",
		"2",
		"27"
	],
	"95030": [
		"5819",
		"4395",
		"467",
		"107",
		"270",
		"254",
		"76",
		"234",
		"16",
		"0"
	],
	"95032": [
		"10652",
		"6080",
		"1622",
		"244",
		"555",
		"632",
		"342",
		"1039",
		"138",
		"0"
	],
	"95033": [
		"4088",
		"3759",
		"122",
		"62",
		"0",
		"0",
		"29",
		"8",
		"76",
		"32"
	],
	"95035": [
		"20839",
		"12030",
		"4181",
		"186",
		"1062",
		"312",
		"431",
		"2149",
		"488",
		"0"
	],
	"95050": [
		"14661",
		"5618",
		"1280",
		"427",
		"1454",
		"1529",
		"1783",
		"2533",
		"0",
		"37"
	],
	"95051": [
		"20963",
		"9929",
		"1926",
		"466",
		"1679",
		"1544",
		"1577",
		"3797",
		"45",
		"0"
	],
	"95053": [
		"24",
		"24",
		"0",
		"0",
		"0",
		"0",
		"0",
		"0",
		"0",
		"0"
	],
	"95054": [
		"8775",
		"2736",
		"1192",
		"168",
		"385",
		"186",
		"1426",
		"2645",
		"26",
		"11"
	],
	"95070": [
		"11583",
		"9642",
		"738",
		"104",
		"267",
		"94",
		"25",
		"659",
		"54",
		"0"
	],
	"95110": [
		"6637",
		"2344",
		"772",
		"264",
		"423",
		"473",
		"551",
		"1803",
		"7",
		"0"
	],
	"95111": [
		"16033",
		"7589",
		"2123",
		"303",
		"747",
		"791",
		"814",
		"1269",
		"2374",
		"23"
	],
	"95112": [
		"20504",
		"6260",
		"1486",
		"1141",
		"1437",
		"2355",
		"1953",
		"4856",
		"953",
		"63"
	],
	"95113": [
		"663",
		"7",
		"0",
		"0",
		"0",
		"10",
		"35",
		"611",
		"0",
		"0"
	],
	"95116": [
		"14139",
		"5861",
		"2091",
		"639",
		"850",
		"1208",
		"819",
		"2140",
		"458",
		"73"
	],
	"95117": [
		"11318",
		"3525",
		"977",
		"508",
		"1493",
		"1213",
		"1156",
		"2397",
		"49",
		"0"
	],
	"95118": [
		"11620",
		"7756",
		"923",
		"164",
		"1022",
		"312",
		"572",
		"846",
		"25",
		"0"
	],
	"95119": [
		"3195",
		"2555",
		"193",
		"60",
		"63",
		"108",
		"44",
		"157",
		"0",
		"15"
	],
	"95120": [
		"12726",
		"11398",
		"1073",
		"67",
		"80",
		"0",
		"0",
		"97",
		"11",
		"0"
	],
	"95121": [
		"9721",
		"6968",
		"1362",
		"29",
		"93",
		"250",
		"192",
		"337",
		"490",
		"0"
	],
	"95122": [
		"13096",
		"7583",
		"927",
		"176",
		"1133",
		"812",
		"676",
		"1249",
		"501",
		"39"
	],
	"95123": [
		"22336",
		"12491",
		"2249",
		"262",
		"1784",
		"954",
		"917",
		"2585",
		"1094",
		"0"
	],
	"95124": [
		"17228",
		"13384",
		"1080",
		"325",
		"815",
		"362",
		"389",
		"873",
		"0",
		"0"
	],
	"95125": [
		"21824",
		"13691",
		"1896",
		"575",
		"372",
		"659",
		"1022",
		"3014",
		"595",
		"0"
	],
	"95126": [
		"14546",
		"4420",
		"1786",
		"561",
		"880",
		"1172",
		"1325",
		"4390",
		"12",
		"0"
	],
	"95127": [
		"17081",
		"13659",
		"1051",
		"151",
		"472",
		"299",
		"414",
		"1006",
		"29",
		"0"
	],
	"95128": [
		"14566",
		"6413",
		"1134",
		"459",
		"1115",
		"1406",
		"1362",
		"2550",
		"127",
		"0"
	],
	"95129": [
		"14657",
		"7944",
		"1711",
		"105",
		"867",
		"418",
		"951",
		"2639",
		"22",
		"0"
	],
	"95130": [
		"5253",
		"3434",
		"367",
		"126",
		"252",
		"188",
		"375",
		"511",
		"0",
		"0"
	],
	"95131": [
		"9335",
		"4535",
		"1972",
		"72",
		"274",
		"751",
		"644",
		"556",
		"531",
		"0"
	],
	"95132": [
		"11994",
		"9099",
		"1238",
		"56",
		"294",
		"417",
		"432",
		"370",
		"67",
		"21"
	],
	"95133": [
		"7881",
		"3763",
		"1227",
		"70",
		"752",
		"617",
		"638",
		"731",
		"83",
		"0"
	],
	"95134": [
		"7133",
		"223",
		"565",
		"91",
		"50",
		"392",
		"316",
		"4266",
		"1230",
		"0"
	],
	"95135": [
		"7452",
		"4455",
		"2081",
		"25",
		"275",
		"203",
		"98",
		"315",
		"0",
		"0"
	],
	"95136": [
		"15372",
		"6954",
		"1981",
		"105",
		"594",
		"1456",
		"1344",
		"1691",
		"1247",
		"0"
	],
	"95138": [
		"6063",
		"4191",
		"684",
		"30",
		"101",
		"189",
		"121",
		"203",
		"544",
		"0"
	],
	"95139": [
		"2297",
		"1847",
		"304",
		"0",
		"14",
		"29",
		"0",
		"103",
		"0",
		"0"
	],
	"95140": [
		"117",
		"117",
		"0",
		"0",
		"0",
		"0",
		"0",
		"0",
		"0",
		"0"
	],
	"95148": [
		"11772",
		"10396",
		"558",
		"44",
		"78",
		"139",
		"152",
		"61",
		"304",
		"40"
	]
}